README.md
setup.py
Appium_Flutter_Finder.egg-info/PKG-INFO
Appium_Flutter_Finder.egg-info/SOURCES.txt
Appium_Flutter_Finder.egg-info/dependency_links.txt
Appium_Flutter_Finder.egg-info/requires.txt
Appium_Flutter_Finder.egg-info/top_level.txt
appium_flutter_finder/__init__.py
appium_flutter_finder/flutter_finder.py