Metadata-Version: 2.1
Name: Appium-Flutter-Finder
Version: 0.5.0
Summary: An extention of finder for Appium flutter
Home-page: https://github.com/appium-userland/appium-flutter-driver
Author: Kazuaki Matsuo
Author-email: fly.49.89.over@gmail.com
License: MIT
Keywords: appium,flutter,python client,mobile automation
Platform: UNKNOWN
Classifier: Development Status :: 5 - Production/Stable
Classifier: Programming Language :: Python
Classifier: Programming Language :: Python :: 3.7
Classifier: Programming Language :: Python :: 3.8
Classifier: Programming Language :: Python :: 3.9
Classifier: Environment :: Console
Classifier: Environment :: MacOS X
Classifier: Environment :: Win32 (MS Windows)
Classifier: Intended Audience :: Developers
Classifier: Intended Audience :: Other Audience
Classifier: License :: OSI Approved :: MIT License
Classifier: Operating System :: OS Independent
Classifier: Topic :: Software Development :: Quality Assurance
Classifier: Topic :: Software Development :: Testing
